smbmc_exporter/__init__.py
smbmc_exporter/collector.py
smbmc_exporter/console.py
smbmc_exporter-0.1.0.dist-info/entry_points.txt
smbmc_exporter-0.1.0.dist-info/LICENSE
smbmc_exporter-0.1.0.dist-info/WHEEL
smbmc_exporter-0.1.0.dist-info/METADATA
smbmc_exporter-0.1.0.dist-info/RECORD
