Metadata-Version: 2.1
Name: smbmc-exporter
Version: 0.1.0
Summary: Prometheus exporter for smbmc metrics
Home-page: https://github.com/grawlinson/smbmc
License: GPL-3.0-only
Author: George Rawlinson
Author-email: george@rawlinson.net.nz
Requires-Python: >=3.6.1,<4.0.0
Classifier: Development Status :: 4 - Beta
Classifier: Intended Audience :: Developers
Classifier: Intended Audience :: System Administrators
Classifier: License :: OSI Approved :: GNU General Public License v3 (GPLv3)
Classifier: Programming Language :: Python :: 3
Classifier: Programming Language :: Python :: 3.6
Classifier: Programming Language :: Python :: 3.7
Classifier: Programming Language :: Python :: 3.8
Classifier: Programming Language :: Python :: 3.9
Classifier: Topic :: System :: Monitoring
Classifier: Topic :: Utilities
Requires-Dist: click (>=7.1.2,<8.0.0)
Requires-Dist: prometheus-client (>=0.8.0,<0.9.0)
Requires-Dist: smbmc (>=0.2.0,<0.3.0)
Project-URL: Repository, https://github.com/grawlinson/smbmc
